qrnet.py
qrnet-0.1.dist-info/METADATA
qrnet-0.1.dist-info/WHEEL
qrnet-0.1.dist-info/entry_points.txt
qrnet-0.1.dist-info/top_level.txt
qrnet-0.1.dist-info/RECORD
