Metadata-Version: 2.1
Name: qrnet
Version: 0.1
Summary: A simple tool to generate a QR code for Wi-Fi credentials.
Author: Nicholas Trimmer
Author-email: nicholasatrimmer@gmail.com
Classifier: Programming Language :: Python :: 3
Classifier: Operating System :: OS Independent
Requires-Dist: qrcode[pil]
